[
    {
        "nome": "Priscila Carvalho Studio - Manicure em Cataguases",
        "endereco": "R. Cel. João Duarte, 96 - sala311 - Centro, Cataguases - MG, 36770-032, Brazil",
        "telefone": "(999069515)",
        "site": null,
        "avaliacao": 5,
        "horario": "07:00 as 22:30",
        "whatsapp": "32999069515",
        "aprovado": true
    },
    {
        "nome": "Jaque Campos Beauty",
        "endereco": "Edifício Center Shopping - Rua Joaquim Peixoto Ramos, 59 - sala 301 - Centro, Cataguases - MG, 36770-066, Brazil",
        "telefone": "(984963535)",
        "site": "https://www.instagram.com/jaquecamposbeauty/",
        "avaliacao": 5,
        "horario": "09:00 as 20:00",
        "whatsapp": "32984963535",
        "aprovado": true
    },
    {
        "nome": "Salão de beleza - Estúdio Geisa Almeida - Esp. Loiros e mega hair - Corte e etc / Cataguases",
        "endereco": "Atendimento em residência sob agendamentos - R. Francisco Antônio Leonardo, 86 - A - Haidée, Cataguases - MG, 36774-112, Brazil",
        "telefone": "(988064585)",
        "site": null,
        "avaliacao": 5,
        "horario": "01:00 as 18:00",
        "whatsapp": "32988064585",
        "aprovado": true
    },
    {
        "nome": "Luana Beauty Studio | Sobrancelhas e Lash Lifiting em Cataguases MG",
        "endereco": "R. Cap. Marcos, 260 - Vila Minalda, Cataguases - MG, 36772-414, Brazil",
        "telefone": "(998569405)",
        "site": "https://wa.me/5532998569405?text=Oi%2C+vi+seu+studio+no+Google+e+gostaria+de+agendar+um+hor%C3%A1rio.",
        "avaliacao": 5,
        "horario": "01:00 as 19:00",
        "whatsapp": "32998569405",
        "aprovado": true
    },
    {
        "nome": "Espaço Larissa Vieira",
        "endereco": "Predio da Uni Santa - R. Dr. Sobral, 230 - Sala 3 - Centro, Cataguases - MG, 36770-044, Brazil",
        "telefone": "(998046086)",
        "site": null,
        "avaliacao": 5,
        "horario": "08:00 as 20:00",
        "whatsapp": "32998046086",
        "aprovado": true
    },
    {
        "nome": "🏻‍ ️Barbearia Bitarães / Fernando Kids",
        "endereco": "Shopping (ao lado da Plan Minas, Edifício Center - Rua Joaquim Peixoto Ramos, 59 - loja 5 - Centro, Cataguases - MG, 36770-064, Brazil",
        "telefone": "(984375872)",
        "site": "https://linktr.ee/barbeariabitaraes",
        "avaliacao": 5,
        "horario": "09:00 as 19:30",
        "whatsapp": "32984375872",
        "aprovado": true
    },
    {
        "nome": "Salão Lili Sasso",
        "endereco": "Rua Joaquim Peixoto Ramos, 127 - Centro, Cataguases - MG, 36770-066, Brazil",
        "telefone": "(999473214)",
        "site": "https://www.instagram.com/salao.lilisasso/",
        "avaliacao": 5,
        "horario": "09:00 as 18:00",
        "whatsapp": "32999473214",
        "aprovado": true
    },
    {
        "nome": "Espaço Vida em Cachos - Terapia Capilar",
        "endereco": "Tv. Américo Ramos, 67 - Centro, Cataguases - MG, 36770-036, Brazil",
        "telefone": "(34212627)",
        "site": null,
        "avaliacao": 5,
        "horario": "09:00 as 18:30",
        "whatsapp": "3234212627",
        "aprovado": true
    },
    {
        "nome": "Salão Walkíria Castilho",
        "endereco": "R. Francisco Rossi, 94 - Centro, Cataguases - MG, 36770-048, Brazil",
        "telefone": "(34215164)",
        "site": null,
        "avaliacao": 5,
        "horario": "09:00 as 19:00",
        "whatsapp": "3234215164",
        "aprovado": true
    },
    {
        "nome": "RUBINÉIA MENEZES | Salão de Beleza - Cataguases",
        "endereco": "Av. Humberto Mauro, 203 - sala 7 - Centro, Cataguases - MG, 36773-012, Brazil",
        "telefone": "(984502831)",
        "site": "https://www.instagram.com/rubineia_menezes/",
        "avaliacao": 5,
        "horario": "08:00 as 18:00",
        "whatsapp": "32984502831",
        "aprovado": true
    },
    {
        "nome": "Espaço Marcela Ferreira",
        "endereco": "R. Cléber Miranda, 42 - Paraíso, Cataguases - MG, 36772-174, Brazil",
        "telefone": "(998238765)",
        "site": null,
        "avaliacao": 5,
        "horario": "Open 24 hours",
        "whatsapp": "32998238765",
        "aprovado": true
    },
    {
        "nome": "Studio Steffany Lacerda Makeup",
        "endereco": "R. Maj. Viêira, 383 - Centro, Cataguases - MG, 36770-060, Brazil",
        "telefone": null,
        "site": "https://instagram.com/steffanylacerda.makeup?igshid=zrp8zi1wn02n",
        "avaliacao": 5,
        "horario": "Open 24 hours",
        "whatsapp": null,
        "aprovado": true
    },
    {
        "nome": "Bellus Centro Estético",
        "endereco": "Rua Coronel Francisco Vieira, 12 - Centro, Cataguases - MG, 36770-028, Brazil",
        "telefone": "(984161463)",
        "site": null,
        "avaliacao": 5,
        "horario": "09:00 as 20:00",
        "whatsapp": "32984161463",
        "aprovado": true
    },
    {
        "nome": "Salão da Lu",
        "endereco": "R. Dr. Sobral, 445 - Centro, Cataguases - MG, 36770-000, Brazil",
        "telefone": "(34213900)",
        "site": null,
        "avaliacao": 5,
        "horario": "Não Informado",
        "whatsapp": "3234213900",
        "aprovado": true
    },
    {
        "nome": "Beauty Marciléa space",
        "endereco": "Av. Antônio Justino, 151 - Vila Reis, Cataguases - MG, 36770-602, Brazil",
        "telefone": "(34227022)",
        "site": "https://www.youtube.com/watch?v=8jaDOJAS66w",
        "avaliacao": 4.9,
        "horario": "08:00 as 19:00",
        "whatsapp": "3234227022",
        "aprovado": true
    },
    {
        "nome": "Estúdio Fabio Franco",
        "endereco": "Praça Santa Rita, 14 - Centro, Cataguases - MG, 36770-020, Brazil",
        "telefone": "(34227632)",
        "site": "https://instagram.com/estudiofabiofranco?utm_medium=copy_link",
        "avaliacao": 4.9,
        "horario": "09:00 as 19:00",
        "whatsapp": "3234227632",
        "aprovado": true
    },
    {
        "nome": "ESPAÇO ALCIONE ESPINDOLA",
        "endereco": "R. Paulo Matoso - São Diniz, Cataguases - MG, 36774-792, Brazil",
        "telefone": "(984104510)",
        "site": null,
        "avaliacao": 4.9,
        "horario": "07:30 as 19:25",
        "whatsapp": "32984104510",
        "aprovado": true
    },
    {
        "nome": "Salão Talismã",
        "endereco": "R. Maj. Viêira, 131 - Centro, Cataguases - MG, 36770-066, Brazil",
        "telefone": "(34211613)",
        "site": "https://instagram.com/salaotalismacataguases?igshid=108njdd53zo3r",
        "avaliacao": 4.6,
        "horario": "08:00 as 20:00",
        "whatsapp": "3234211613",
        "aprovado": true
    },
    {
        "nome": "Studio Souza- Beleza e Estética",
        "endereco": "R. Olímpio Sacheto - Menezes, Cataguases - MG, 36774-129, Brazil",
        "telefone": "(34216574)",
        "site": "https://instagram.com/studio_souza_beauty",
        "avaliacao": 4.5,
        "horario": "07:00 as 20:00",
        "whatsapp": "3234216574",
        "aprovado": true
    },
    {
        "nome": "Marcela Menezes Studio Beauty",
        "endereco": "Rua Elsie Fajardo da Silveira, 100 - Centro, Cataguases - MG, 36770-076, Brazil",
        "telefone": "(999536700)",
        "site": null,
        "avaliacao": 0,
        "horario": "08:00 as 20:30",
        "whatsapp": "32999536700",
        "aprovado": true
    }
]